bbutil/__init__.py
bbutil/data.py
bbutil/execute.py
bbutil/file.py
bbutil/setup.py
bbutil/utils.py
bbutil/app/__init__.py
bbutil/app/config.py
bbutil/app/console.py
bbutil/app/manager.py
bbutil/app/module.py
bbutil/database/__init__.py
bbutil/database/database.py
bbutil/database/table.py
bbutil/database/types.py
bbutil/database/sqlite/__init__.py
bbutil/database/sqlite/manager.py
bbutil/database/sqlite/types.py
bbutil/lang/__init__.py
bbutil/lang/domain.py
bbutil/lang/parser/__init__.py
bbutil/lang/parser/domain.py
bbutil/lang/parser/language.py
bbutil/lang/parser/pyfile.py
bbutil/logging/__init__.py
bbutil/logging/types.py
bbutil/logging/writer/__init__.py
bbutil/logging/writer/console.py
bbutil/logging/writer/file.py
bbutil/logging/writer/qt.py
bbutil/logging/writer/tkinter.py
bbutil/worker/__init__.py
bbutil/worker/callback.py
bbutils-0.7.0.0.data/scripts/make-lang.py
bbutils-0.7.0.0.data/scripts/run-tests.py
tests/app/__init__.py
tests/app/config.py
tests/app/console.py
tests/app/manager.py
tests/app/module.py
tests/database/__init__.py
tests/database/database.py
tests/database/manager.py
tests/database/sqlite.py
tests/database/table.py
tests/helper/__init__.py
tests/helper/config.py
tests/helper/console.py
tests/helper/database.py
tests/helper/execute.py
tests/helper/file.py
tests/helper/module.py
tests/helper/setup.py
tests/helper/sqlite.py
tests/helper/table.py
tests/helper/worker.py
bbutils-0.7.0.0.dist-info/LICENSE
bbutils-0.7.0.0.dist-info/METADATA
bbutils-0.7.0.0.dist-info/WHEEL
bbutils-0.7.0.0.dist-info/top_level.txt
bbutils-0.7.0.0.dist-info/RECORD
