Metadata-Version: 2.1
Name: bbutils
Version: 0.7.0.0
Summary: Small collection of stuff for all my other python projects (including logging).
Home-page: https://github.com/TheUncleKai/bbutils
Author: Kai Raphahn
Author-email: kai.raphahn@laburec.de
License: Apache License, Version 2.0
Classifier: Development Status :: 4 - Beta
Classifier: License :: OSI Approved :: Apache Software License
Classifier: Intended Audience :: Developers
Classifier: Topic :: Software Development :: Libraries
Requires-Python: >=3.6
License-File: LICENSE
Requires-Dist: colorama
